PyBH/__init__.py
PyBH/main.py
PyBH-1.0.0.dist-info/LICENCE.txt
PyBH-1.0.0.dist-info/METADATA
PyBH-1.0.0.dist-info/WHEEL
PyBH-1.0.0.dist-info/top_level.txt
PyBH-1.0.0.dist-info/RECORD
