Metadata-Version: 2.2
Name: PyBH
Version: 1.0.0
Summary: Votre module qui dépend de Matplotlib et Pandas
Home-page: https://github.com/MrgAch
Author: Achour Margoum
Author-email: margoumachour@gmail.com
Classifier: Programming Language :: Python :: 3
Classifier: License :: OSI Approved :: MIT License
Classifier: Operating System :: OS Independent
Requires-Python: >=3.10
License-File: LICENCE.txt
Requires-Dist: matplotlib
Requires-Dist: pandas
Requires-Dist: numpy
Dynamic: author
Dynamic: author-email
Dynamic: classifier
Dynamic: description
Dynamic: description-content-type
Dynamic: home-page
Dynamic: requires-dist
Dynamic: requires-python
Dynamic: summary
